{
  "basics": {
    "name": "Nanami Kimoto",
    "label": "Student",
    "picture": "nakimoto.github.io/images/2D57D800-9115-4F15-9718-7D7BB351C347_1_201_a.jpeg",
    "email": "nkimoto@hawaii.edu",
    "phone": "",
    "website": "https://www.nakimoto.github.io",
    "summary": "I am an undergraduate student studying Computer Science for my B.S. I currently work at JABSOM as a computer science student researcher and I am an undergraduate fellow at the Hawaii Data Science Institute.",
    "location": {
      "address": "",
      "postalCode": "96818",
      "city": "Honolulu",
      "countryCode": "USA",
      "region": "Hawaii"
    },
    "profiles": [
      {
        "network": "github",
        "username": "nakimoto",
        "url": "https://www.github.com/nakimoto"
      },
      {
        "network": "linkedin",
        "username": "nnmkmt",
        "url": "https://www.linkedin.com/in/nnmkmt/"
      },
 
     
    ]
  },
  "interests": [
    {
      "name": "Quantum Computing",
    
    },
    {
      "name": "Robotics",
      
    },
    {
      "name": "Artificial Intelligence",
      
    }
  ],
  "skills": [
    {
      "name": "Languages and Frameworks",
      "level": "",
      "keywords": [
        "C++",
        "Java",
        "Javascript",
        "Python",
        
      ]
    },
    {
      "name": "Toolsets/OS",
      "level": "",
      "keywords": [
        "MacOS",
        "Ubuntu",
        "Git/GitHub",
        
        
      ]
    }
  ],
  "education": [
    {
      "institution": "University of Hawaii at Manoa, Honolulu, HI",
      "area": "Computer Science (expected graduation fall, 2021)",
      "studyType": "B.S.",
    
    }
  ],
  "work": [
    {
      "company": "John A. Burns School of Medicine",
      "position": "Computer Science Research Student",
      
      "startDate": "2020-06-01",
      "endDate": "Present",
      "summary": "Computer Science themes research projects",
      "highlights": [
        "Built an HPC for the laboratory"
        
      ]
    },
    {
      "company": "Hawaii Data Science Institute",
      "position": "Undergraduate Research Fellow",
      "website": "https://datascience.hawaii.edu",
      "startDate": "2020-08-27",
      "endDate": "Present",
      "summary": "Semester long Data Science research projects",
      "highlights": [
        "DOD Global Terrorism Database project",
        "MOKU medicinal plants project"
      ]
    }
  ],
  "volunteer": [
    {
      "organization": "Doctors Without Borders",
      "website": "https://www.doctorswithoutborders.org",
      "position": "Mapathon volunteer",
      "highlights": [
        "Use mapping software to help determine areas or the world that need humanitarian aid",
        
      ]
    },
    
  ],

   
 
  "references": [
    {
      "name": "Available upon request",
      "reference": ""
    }
  ]
}
